{"platplus": {"JUNGLE": {"skill_order": ["q", "e", "w", "e", "q", "r", "e", "q", "e", "e", "r", "q", "q", "w", "w", "r", "w", "w"], "stats": {"Win Rate": "48.82%", "Pick Rate": "4.62%", "Ban Rate": "1.07%", "Gold Earned": "12073", "Kills": "8.11", "Deaths": "6.55", "Assists": "4.65", "Damage Dealt": "16582.70", "Damage Taken": "27906.70", "Minions Killed": "61"}}}, "skillImages": ["https://ddragon.leagueoflegends.com/cdn/7.14.1/img/spell/AlphaStrike.png", "https://ddragon.leagueoflegends.com/cdn/7.14.1/img/spell/Meditate.png", "https://ddragon.leagueoflegends.com/cdn/7.14.1/img/spell/WujuStyle.png", "https://ddragon.leagueoflegends.com/cdn/7.14.1/img/spell/Highlander.png"], "plat": {"JUNGLE": {"skill_order": ["q", "e", "w", "e", "q", "r", "q", "w", "q", "e", "r", "q", "e", "e", "r", "w", "w", "w"], "stats": {"Win Rate": "49.55%", "Pick Rate": "5.57%", "Ban Rate": "1.42%", "Gold Earned": "12201", "Kills": "8.24", "Deaths": "6.64", "Assists": "4.74", "Damage Dealt": "16851.60", "Damage Taken": "28279.90", "Minions Killed": "62"}}}, "gold": {"JUNGLE": {"skill_order": ["q", "e", "w", "e", "e", "r", "q", "q", "q", "q", "r", "e", "e", "w", "w", "r", "w", "w"], "stats": {"Win Rate": "50.06%", "Pick Rate": "7.10%", "Ban Rate": "2.21%", "Gold Earned": "12321", "Kills": "8.39", "Deaths": "6.84", "Assists": "4.89", "Damage Dealt": "17122.90", "Damage Taken": "28798.10", "Minions Killed": "62"}}}, "silver": {"JUNGLE": {"skill_order": ["e", "w", "q", "q", "q", "r", "q", "e", "q", "e", "r", "e", "e", "w", "w", "r", "w", "w"], "stats": {"Win Rate": "50.51%", "Pick Rate": "8.94%", "Ban Rate": "3.16%", "Gold Earned": "12376", "Kills": "8.47", "Deaths": "7.08", "Assists": "5.07", "Damage Dealt": "17318.70", "Damage Taken": "29033.90", "Minions Killed": "64"}}}, "bronze": {"JUNGLE": {"skill_order": ["e", "q", "w", "q", "e", "r", "e", "e", "q", "e", "r", "q", "q", "w", "w", "r", "w", "w"], "stats": {"Win Rate": "51.76%", "Pick Rate": "11.31%", "Ban Rate": "3.98%", "Gold Earned": "12456", "Kills": "8.71", "Deaths": "7.43", "Assists": "5.33", "Damage Dealt": "17941.50", "Damage Taken": "29411.10", "Minions Killed": "65"}}}}