{"platplus": {"JUNGLE": {"skill_order": ["e", "w", "q", "w", "w", "r", "w", "q", "w", "q", "r", "q", "q", "e", "e", "r", "e", "e"], "stats": {"Win Rate": "54.18%", "Pick Rate": "4.86%", "Ban Rate": "1.29%", "Gold Earned": "10467", "Kills": "4.21", "Deaths": "4.91", "Assists": "10.97", "Damage Dealt": "12264.70", "Damage Taken": "28480.50", "Minions Killed": "37"}, "build": [{"src": "https://ddragon.leagueoflegends.com/cdn/7.14.1/img/item/1413.png", "id": "1413"}, {"src": "https://ddragon.leagueoflegends.com/cdn/7.14.1/img/item/3047.png", "id": "3047"}, {"src": "https://ddragon.leagueoflegends.com/cdn/7.14.1/img/item/3075.png", "id": "3075"}, {"src": "https://ddragon.leagueoflegends.com/cdn/7.14.1/img/item/3800.png", "id": "3800"}, {"src": "https://ddragon.leagueoflegends.com/cdn/7.14.1/img/item/3193.png", "id": "3193"}, {"src": "https://ddragon.leagueoflegends.com/cdn/7.14.1/img/item/3143.png", "id": "3143"}], "counters": {"weak": [{"name": "Shaco", "win_rate": "49.10%", "img": "https://ddragon.leagueoflegends.com/cdn/7.19.1/img/champion/Shaco.png"}, {"name": "Pantheon", "win_rate": "49.14%", "img": "https://ddragon.leagueoflegends.com/cdn/7.19.1/img/champion/Pantheon.png"}, {"name": "ChoGath", "win_rate": "49.27%", "img": "https://ddragon.leagueoflegends.com/cdn/7.19.1/img/champion/Chogath.png"}, {"name": "Fiddlesticks", "win_rate": "49.30%", "img": "https://ddragon.leagueoflegends.com/cdn/7.19.1/img/champion/Fiddlesticks.png"}, {"name": "Nunu", "win_rate": "49.51%", "img": "https://ddragon.leagueoflegends.com/cdn/7.19.1/img/champion/Nunu.png"}], "strong": [{"name": "Tryndamere", "win_rate": "61.86%", "img": "https://ddragon.leagueoflegends.com/cdn/7.19.1/img/champion/Tryndamere.png"}, {"name": "Nautilus", "win_rate": "61.68%", "img": "https://ddragon.leagueoflegends.com/cdn/7.19.1/img/champion/Nautilus.png"}, {"name": "Poppy", "win_rate": "60.00%", "img": "https://ddragon.leagueoflegends.com/cdn/7.19.1/img/champion/Poppy.png"}, {"name": "Kindred", "win_rate": "59.68%", "img": "https://ddragon.leagueoflegends.com/cdn/7.19.1/img/champion/Kindred.png"}, {"name": "Graves", "win_rate": "59.60%", "img": "https://ddragon.leagueoflegends.com/cdn/7.19.1/img/champion/Graves.png"}]}}}, "skillImages": ["https://ddragon.leagueoflegends.com/cdn/7.14.1/img/spell/PowerBall.png", "https://ddragon.leagueoflegends.com/cdn/7.14.1/img/spell/DefensiveBallCurl.png", "https://ddragon.leagueoflegends.com/cdn/7.14.1/img/spell/PuncturingTaunt.png", "https://ddragon.leagueoflegends.com/cdn/7.14.1/img/spell/Tremors2.png"], "plat": {"JUNGLE": {"skill_order": ["e", "w", "q", "e", "e", "r", "e", "q", "e", "q", "r", "q", "q", "w", "w", "r", "w", "w"], "stats": {"Win Rate": "54.27%", "Pick Rate": "4.65%", "Ban Rate": "1.09%", "Gold Earned": "10580", "Kills": "4.29", "Deaths": "5.02", "Assists": "11.15", "Damage Dealt": "12493.80", "Damage Taken": "28819.90", "Minions Killed": "38"}, "build": [{"src": "https://ddragon.leagueoflegends.com/cdn/7.14.1/img/item/1401.png", "id": "1401"}, {"src": "https://ddragon.leagueoflegends.com/cdn/7.14.1/img/item/3047.png", "id": "3047"}, {"src": "https://ddragon.leagueoflegends.com/cdn/7.14.1/img/item/3075.png", "id": "3075"}, {"src": "https://ddragon.leagueoflegends.com/cdn/7.14.1/img/item/3800.png", "id": "3800"}, {"src": "https://ddragon.leagueoflegends.com/cdn/7.14.1/img/item/3193.png", "id": "3193"}, {"src": "https://ddragon.leagueoflegends.com/cdn/7.14.1/img/item/3110.png", "id": "3110"}], "counters": {"weak": [{"name": "ChoGath", "win_rate": "43.93%", "img": "https://ddragon.leagueoflegends.com/cdn/7.19.1/img/champion/Chogath.png"}, {"name": "Udyr", "win_rate": "47.97%", "img": "https://ddragon.leagueoflegends.com/cdn/7.19.1/img/champion/Udyr.png"}, {"name": "Dr. Mundo", "win_rate": "49.68%", "img": "https://ddragon.leagueoflegends.com/cdn/7.19.1/img/champion/DrMundo.png"}, {"name": "Ivern", "win_rate": "50.19%", "img": "https://ddragon.leagueoflegends.com/cdn/7.19.1/img/champion/Ivern.png"}, {"name": "Xin Zhao", "win_rate": "50.71%", "img": "https://ddragon.leagueoflegends.com/cdn/7.19.1/img/champion/XinZhao.png"}], "strong": [{"name": "Graves", "win_rate": "60.69%", "img": "https://ddragon.leagueoflegends.com/cdn/7.19.1/img/champion/Graves.png"}, {"name": "Olaf", "win_rate": "59.40%", "img": "https://ddragon.leagueoflegends.com/cdn/7.19.1/img/champion/Olaf.png"}, {"name": "Ornn", "win_rate": "58.40%", "img": "https://ddragon.leagueoflegends.com/cdn/7.19.1/img/champion/Ornn.png"}, {"name": "Poppy", "win_rate": "57.83%", "img": "https://ddragon.leagueoflegends.com/cdn/7.19.1/img/champion/Poppy.png"}, {"name": "Kindred", "win_rate": "57.77%", "img": "https://ddragon.leagueoflegends.com/cdn/7.19.1/img/champion/Kindred.png"}]}}}, "gold": {"JUNGLE": {"skill_order": ["w", "q", "e", "q", "e", "r", "e", "q", "q", "q", "r", "e", "e", "w", "w", "r", "w", "w"], "stats": {"Win Rate": "54.15%", "Pick Rate": "3.91%", "Ban Rate": "0.68%", "Gold Earned": "10803", "Kills": "4.52", "Deaths": "5.30", "Assists": "11.38", "Damage Dealt": "13078.10", "Damage Taken": "29547.10", "Minions Killed": "41"}, "build": [{"src": "https://ddragon.leagueoflegends.com/cdn/7.14.1/img/item/1401.png", "id": "1401"}, {"src": "https://ddragon.leagueoflegends.com/cdn/7.14.1/img/item/3009.png", "id": "3009"}, {"src": "https://ddragon.leagueoflegends.com/cdn/7.14.1/img/item/3075.png", "id": "3075"}, {"src": "https://ddragon.leagueoflegends.com/cdn/7.14.1/img/item/3742.png", "id": "3742"}, {"src": "https://ddragon.leagueoflegends.com/cdn/7.14.1/img/item/3143.png", "id": "3143"}, {"src": "https://ddragon.leagueoflegends.com/cdn/7.14.1/img/item/3110.png", "id": "3110"}], "counters": {"weak": [{"name": "Dr. Mundo", "win_rate": "47.22%", "img": "https://ddragon.leagueoflegends.com/cdn/7.19.1/img/champion/DrMundo.png"}, {"name": "Pantheon", "win_rate": "47.32%", "img": "https://ddragon.leagueoflegends.com/cdn/7.19.1/img/champion/Pantheon.png"}, {"name": "Sejuani", "win_rate": "47.37%", "img": "https://ddragon.leagueoflegends.com/cdn/7.19.1/img/champion/Sejuani.png"}, {"name": "Shyvana", "win_rate": "47.76%", "img": "https://ddragon.leagueoflegends.com/cdn/7.19.1/img/champion/Shyvana.png"}, {"name": "Nunu", "win_rate": "48.39%", "img": "https://ddragon.leagueoflegends.com/cdn/7.19.1/img/champion/Nunu.png"}], "strong": [{"name": "Tryndamere", "win_rate": "66.67%", "img": "https://ddragon.leagueoflegends.com/cdn/7.19.1/img/champion/Tryndamere.png"}, {"name": "Graves", "win_rate": "60.11%", "img": "https://ddragon.leagueoflegends.com/cdn/7.19.1/img/champion/Graves.png"}, {"name": "Nidalee", "win_rate": "59.59%", "img": "https://ddragon.leagueoflegends.com/cdn/7.19.1/img/champion/Nidalee.png"}, {"name": "Diana", "win_rate": "58.96%", "img": "https://ddragon.leagueoflegends.com/cdn/7.19.1/img/champion/Diana.png"}, {"name": "Kindred", "win_rate": "58.87%", "img": "https://ddragon.leagueoflegends.com/cdn/7.19.1/img/champion/Kindred.png"}]}}}, "silver": {"JUNGLE": {"skill_order": ["e", "w", "q", "e", "e", "r", "e", "q", "e", "q", "r", "q", "q", "w", "w", "r", "w", "w"], "stats": {"Win Rate": "53.98%", "Pick Rate": "3.38%", "Ban Rate": "0.45%", "Gold Earned": "10880", "Kills": "4.60", "Deaths": "5.49", "Assists": "11.54", "Damage Dealt": "13315.80", "Damage Taken": "29729.90", "Minions Killed": "42"}, "build": [{"src": "https://ddragon.leagueoflegends.com/cdn/7.14.1/img/item/1401.png", "id": "1401"}, {"src": "https://ddragon.leagueoflegends.com/cdn/7.14.1/img/item/3009.png", "id": "3009"}, {"src": "https://ddragon.leagueoflegends.com/cdn/7.14.1/img/item/3075.png", "id": "3075"}, {"src": "https://ddragon.leagueoflegends.com/cdn/7.14.1/img/item/3742.png", "id": "3742"}, {"src": "https://ddragon.leagueoflegends.com/cdn/7.14.1/img/item/3193.png", "id": "3193"}, {"src": "https://ddragon.leagueoflegends.com/cdn/7.14.1/img/item/3143.png", "id": "3143"}], "counters": {"weak": [{"name": "Shyvana", "win_rate": "47.97%", "img": "https://ddragon.leagueoflegends.com/cdn/7.19.1/img/champion/Shyvana.png"}, {"name": "Trundle", "win_rate": "48.28%", "img": "https://ddragon.leagueoflegends.com/cdn/7.19.1/img/champion/Trundle.png"}, {"name": "Xin Zhao", "win_rate": "48.83%", "img": "https://ddragon.leagueoflegends.com/cdn/7.19.1/img/champion/XinZhao.png"}, {"name": "Sejuani", "win_rate": "49.37%", "img": "https://ddragon.leagueoflegends.com/cdn/7.19.1/img/champion/Sejuani.png"}, {"name": "Vi", "win_rate": "49.41%", "img": "https://ddragon.leagueoflegends.com/cdn/7.19.1/img/champion/Vi.png"}], "strong": [{"name": "Olaf", "win_rate": "60.55%", "img": "https://ddragon.leagueoflegends.com/cdn/7.19.1/img/champion/Olaf.png"}, {"name": "Shaco", "win_rate": "59.82%", "img": "https://ddragon.leagueoflegends.com/cdn/7.19.1/img/champion/Shaco.png"}, {"name": "Kindred", "win_rate": "58.56%", "img": "https://ddragon.leagueoflegends.com/cdn/7.19.1/img/champion/Kindred.png"}, {"name": "Zac", "win_rate": "58.30%", "img": "https://ddragon.leagueoflegends.com/cdn/7.19.1/img/champion/Zac.png"}, {"name": "Volibear", "win_rate": "58.20%", "img": "https://ddragon.leagueoflegends.com/cdn/7.19.1/img/champion/Volibear.png"}]}}}, "bronze": {"JUNGLE": {"skill_order": ["e", "w", "q", "e", "e", "r", "e", "w", "e", "w", "r", "w", "w", "q", "q", "r", "q", "q"], "stats": {"Win Rate": "53.65%", "Pick Rate": "2.91%", "Ban Rate": "0.27%", "Gold Earned": "10935", "Kills": "4.80", "Deaths": "5.91", "Assists": "11.52", "Damage Dealt": "13746.20", "Damage Taken": "30017.60", "Minions Killed": "44"}, "build": [{"src": "https://ddragon.leagueoflegends.com/cdn/7.14.1/img/item/1401.png", "id": "1401"}, {"src": "https://ddragon.leagueoflegends.com/cdn/7.14.1/img/item/3009.png", "id": "3009"}, {"src": "https://ddragon.leagueoflegends.com/cdn/7.14.1/img/item/3075.png", "id": "3075"}, {"src": "https://ddragon.leagueoflegends.com/cdn/7.14.1/img/item/3742.png", "id": "3742"}, {"src": "https://ddragon.leagueoflegends.com/cdn/7.14.1/img/item/3143.png", "id": "3143"}, {"src": "https://ddragon.leagueoflegends.com/cdn/7.14.1/img/item/3194.png", "id": "3194"}], "counters": {"weak": [{"name": "ChoGath", "win_rate": "45.00%", "img": "https://ddragon.leagueoflegends.com/cdn/7.19.1/img/champion/Chogath.png"}, {"name": "Amumu", "win_rate": "46.24%", "img": "https://ddragon.leagueoflegends.com/cdn/7.19.1/img/champion/Amumu.png"}, {"name": "Maokai", "win_rate": "46.25%", "img": "https://ddragon.leagueoflegends.com/cdn/7.19.1/img/champion/Maokai.png"}, {"name": "Graves", "win_rate": "47.13%", "img": "https://ddragon.leagueoflegends.com/cdn/7.19.1/img/champion/Graves.png"}, {"name": "Nidalee", "win_rate": "47.37%", "img": "https://ddragon.leagueoflegends.com/cdn/7.19.1/img/champion/Nidalee.png"}], "strong": [{"name": "Rengar", "win_rate": "62.82%", "img": "https://ddragon.leagueoflegends.com/cdn/7.19.1/img/champion/Rengar.png"}, {"name": "Shaco", "win_rate": "62.75%", "img": "https://ddragon.leagueoflegends.com/cdn/7.19.1/img/champion/Shaco.png"}, {"name": "Kindred", "win_rate": "60.53%", "img": "https://ddragon.leagueoflegends.com/cdn/7.19.1/img/champion/Kindred.png"}, {"name": "Pantheon", "win_rate": "59.21%", "img": "https://ddragon.leagueoflegends.com/cdn/7.19.1/img/champion/Pantheon.png"}, {"name": "Gragas", "win_rate": "59.05%", "img": "https://ddragon.leagueoflegends.com/cdn/7.19.1/img/champion/Gragas.png"}]}}}}