{"platplus": {"JUNGLE": {"skill_order": ["q", "w", "e", "w", "q", "r", "q", "q", "q", "e", "r", "e", "w", "w", "w", "r", "e", "e"], "stats": {"Win Rate": "49.45%", "Pick Rate": "2.26%", "Ban Rate": "0.11%", "Gold Earned": "11515", "Kills": "7.46", "Deaths": "6.03", "Assists": "5.91", "Damage Dealt": "16461.50", "Damage Taken": "27772.70", "Minions Killed": "44"}}, "TOP": {"skill_order": ["q", "e", "w", "q", "e", "r", "q", "q", "q", "e", "r", "e", "e", "w", "w", "r", "w", "w"], "stats": {"Win Rate": "51.96%", "Pick Rate": "0.69%", "Ban Rate": "0.11%", "Gold Earned": "11700", "Kills": "7.67", "Deaths": "6.28", "Assists": "5.03", "Damage Dealt": "19215.30", "Damage Taken": "24228.80", "Minions Killed": "158"}}}, "skillImages": ["https://ddragon.leagueoflegends.com/cdn/7.14.1/img/spell/RengarQ.png", "https://ddragon.leagueoflegends.com/cdn/7.14.1/img/spell/RengarW.png", "https://ddragon.leagueoflegends.com/cdn/7.14.1/img/spell/RengarE.png", "https://ddragon.leagueoflegends.com/cdn/7.14.1/img/spell/RengarR.png"], "plat": {"JUNGLE": {"skill_order": ["q", "w", "e", "e", "q", "r", "q", "q", "q", "e", "r", "e", "e", "w", "w", "r", "w", "w"], "stats": {"Win Rate": "48.82%", "Pick Rate": "2.15%", "Ban Rate": "0.10%", "Gold Earned": "11613", "Kills": "7.50", "Deaths": "6.25", "Assists": "5.96", "Damage Dealt": "16526.50", "Damage Taken": "28326.50", "Minions Killed": "45"}}, "TOP": {"skill_order": ["q", "e", "w", "q", "q", "r", "q", "e", "e", "q", "r", "e", "e", "w", "w", "r", "w", "w"], "stats": {"Win Rate": "50.52%", "Pick Rate": "0.66%", "Ban Rate": "0.10%", "Gold Earned": "11897", "Kills": "7.95", "Deaths": "6.64", "Assists": "5.13", "Damage Dealt": "19742.40", "Damage Taken": "24955.20", "Minions Killed": "157"}}}, "gold": {"JUNGLE": {"skill_order": ["q", "e", "w", "w", "q", "r", "q", "q", "q", "e", "r", "e", "e", "e", "w", "r", "w", "w"], "stats": {"Win Rate": "47.04%", "Pick Rate": "2.04%", "Ban Rate": "0.10%", "Gold Earned": "11762", "Kills": "7.61", "Deaths": "6.68", "Assists": "6.11", "Damage Dealt": "16764.50", "Damage Taken": "29241.70", "Minions Killed": "47"}}, "TOP": {"skill_order": ["q", "e", "w", "q", "q", "r", "q", "e", "q", "e", "r", "e", "e", "w", "w", "r", "w", "w"], "stats": {"Win Rate": "49.41%", "Pick Rate": "0.59%", "Ban Rate": "0.10%", "Gold Earned": "12195", "Kills": "8.46", "Deaths": "7.00", "Assists": "5.30", "Damage Dealt": "20873.40", "Damage Taken": "26043.60", "Minions Killed": "157"}}}, "silver": {"JUNGLE": {"skill_order": ["q", "w", "w", "e", "q", "r", "w", "q", "q", "q", "r", "w", "w", "e", "e", "r", "e", "e"], "stats": {"Win Rate": "46.94%", "Pick Rate": "2.10%", "Ban Rate": "0.11%", "Gold Earned": "11815", "Kills": "7.65", "Deaths": "7.05", "Assists": "6.14", "Damage Dealt": "16705.10", "Damage Taken": "29759.40", "Minions Killed": "48"}}, "TOP": {"skill_order": ["q", "e", "w", "q", "q", "r", "q", "e", "e", "q", "r", "e", "e", "w", "w", "r", "w", "w"], "stats": {"Win Rate": "50.52%", "Pick Rate": "0.58%", "Ban Rate": "0.11%", "Gold Earned": "12020", "Kills": "8.67", "Deaths": "7.18", "Assists": "5.24", "Damage Dealt": "20732.70", "Damage Taken": "25757.80", "Minions Killed": "149"}}}, "bronze": {"JUNGLE": {"skill_order": ["q", "w", "q", "e", "q", "r", "e", "q", "q", "e", "r", "e", "e", "w", "w", "r", "w", "w"], "stats": {"Win Rate": "45.40%", "Pick Rate": "2.16%", "Ban Rate": "0.14%", "Gold Earned": "11729", "Kills": "7.65", "Deaths": "7.49", "Assists": "6.18", "Damage Dealt": "16534.40", "Damage Taken": "30034.60", "Minions Killed": "47"}}, "TOP": {"skill_order": ["q", "e", "w", "q", "q", "r", "q", "e", "q", "e", "r", "e", "e", "w", "w", "r", "w", "w"], "stats": {"Win Rate": "47.73%", "Pick Rate": "0.55%", "Ban Rate": "0.14%", "Gold Earned": "12112", "Kills": "9.02", "Deaths": "7.85", "Assists": "5.24", "Damage Dealt": "21193.50", "Damage Taken": "26913.00", "Minions Killed": "143"}}}}