{"platplus": {"MIDDLE": {"skill_order": ["w", "q", "e", "w", "q", "r", "w", "q", "q", "q", "r", "e", "w", "w", "e", "r", "e", "e"], "stats": {"Win Rate": "52.54%", "Pick Rate": "2.41%", "Ban Rate": "0.05%", "Gold Earned": "11784", "Kills": "6.82", "Deaths": "5.40", "Assists": "7.68", "Damage Dealt": "24710.30", "Damage Taken": "15945.10", "Minions Killed": "173"}, "build": [{"src": "https://ddragon.leagueoflegends.com/cdn/7.14.1/img/item/3165.png", "id": "3165"}, {"src": "https://ddragon.leagueoflegends.com/cdn/7.14.1/img/item/3020.png", "id": "3020"}, {"src": "https://ddragon.leagueoflegends.com/cdn/7.14.1/img/item/3285.png", "id": "3285"}, {"src": "https://ddragon.leagueoflegends.com/cdn/7.14.1/img/item/3151.png", "id": "3151"}, {"src": "https://ddragon.leagueoflegends.com/cdn/7.14.1/img/item/3135.png", "id": "3135"}, {"src": "https://ddragon.leagueoflegends.com/cdn/7.14.1/img/item/3089.png", "id": "3089"}], "counters": {"weak": [{"name": "Ahri", "win_rate": "45.73%", "img": "https://ddragon.leagueoflegends.com/cdn/7.19.1/img/champion/Ahri.png"}, {"name": "Kennen", "win_rate": "46.15%", "img": "https://ddragon.leagueoflegends.com/cdn/7.19.1/img/champion/Kennen.png"}, {"name": "Ziggs", "win_rate": "47.53%", "img": "https://ddragon.leagueoflegends.com/cdn/7.19.1/img/champion/Ziggs.png"}, {"name": "Fizz", "win_rate": "48.13%", "img": "https://ddragon.leagueoflegends.com/cdn/7.19.1/img/champion/Fizz.png"}, {"name": "Heimerdinger", "win_rate": "48.25%", "img": "https://ddragon.leagueoflegends.com/cdn/7.19.1/img/champion/Heimerdinger.png"}], "strong": [{"name": "Azir", "win_rate": "60.94%", "img": "https://ddragon.leagueoflegends.com/cdn/7.19.1/img/champion/Azir.png"}, {"name": "Galio", "win_rate": "58.47%", "img": "https://ddragon.leagueoflegends.com/cdn/7.19.1/img/champion/Galio.png"}, {"name": "Jayce", "win_rate": "56.77%", "img": "https://ddragon.leagueoflegends.com/cdn/7.19.1/img/champion/Jayce.png"}, {"name": "Akali", "win_rate": "56.55%", "img": "https://ddragon.leagueoflegends.com/cdn/7.19.1/img/champion/Akali.png"}, {"name": "Morgana", "win_rate": "56.47%", "img": "https://ddragon.leagueoflegends.com/cdn/7.19.1/img/champion/Morgana.png"}]}}, "SUPPORT": {"skill_order": ["q", "w", "q", "e", "q", "r", "q", "w", "q", "w", "r", "w", "w", "e", "e", "r", "e", "e"], "stats": {"Win Rate": "48.50%", "Pick Rate": "0.83%", "Ban Rate": "0.05%", "Gold Earned": "10655", "Kills": "4.68", "Deaths": "6.24", "Assists": "10.16", "Damage Dealt": "21348.10", "Damage Taken": "15352.90", "Minions Killed": "44"}, "build": [{"src": "https://ddragon.leagueoflegends.com/cdn/7.14.1/img/item/2301.png", "id": "2301"}, {"src": "https://ddragon.leagueoflegends.com/cdn/7.14.1/img/item/3020.png", "id": "3020"}, {"src": "https://ddragon.leagueoflegends.com/cdn/7.14.1/img/item/3151.png", "id": "3151"}, {"src": "https://ddragon.leagueoflegends.com/cdn/7.14.1/img/item/3116.png", "id": "3116"}, {"src": "https://ddragon.leagueoflegends.com/cdn/7.14.1/img/item/3135.png", "id": "3135"}, {"src": "https://ddragon.leagueoflegends.com/cdn/7.14.1/img/item/3285.png", "id": "3285"}], "counters": {"weak": [{"name": "Sona", "win_rate": "43.13%", "img": "https://ddragon.leagueoflegends.com/cdn/7.19.1/img/champion/Sona.png"}, {"name": "Janna", "win_rate": "43.77%", "img": "https://ddragon.leagueoflegends.com/cdn/7.19.1/img/champion/Janna.png"}, {"name": "Soraka", "win_rate": "44.21%", "img": "https://ddragon.leagueoflegends.com/cdn/7.19.1/img/champion/Soraka.png"}, {"name": "Alistar", "win_rate": "46.15%", "img": "https://ddragon.leagueoflegends.com/cdn/7.19.1/img/champion/Alistar.png"}, {"name": "Zilean", "win_rate": "46.43%", "img": "https://ddragon.leagueoflegends.com/cdn/7.19.1/img/champion/Zilean.png"}], "strong": [{"name": "Braum", "win_rate": "53.05%", "img": "https://ddragon.leagueoflegends.com/cdn/7.19.1/img/champion/Braum.png"}, {"name": "Lux", "win_rate": "52.63%", "img": "https://ddragon.leagueoflegends.com/cdn/7.19.1/img/champion/Lux.png"}, {"name": "Brand", "win_rate": "52.23%", "img": "https://ddragon.leagueoflegends.com/cdn/7.19.1/img/champion/Brand.png"}, {"name": "Thresh", "win_rate": "51.32%", "img": "https://ddragon.leagueoflegends.com/cdn/7.19.1/img/champion/Thresh.png"}, {"name": "Rakan", "win_rate": "50.30%", "img": "https://ddragon.leagueoflegends.com/cdn/7.19.1/img/champion/Rakan.png"}]}}}, "skillImages": ["https://ddragon.leagueoflegends.com/cdn/7.14.1/img/spell/VelkozQ.png", "https://ddragon.leagueoflegends.com/cdn/7.14.1/img/spell/VelkozW.png", "https://ddragon.leagueoflegends.com/cdn/7.14.1/img/spell/VelkozE.png", "https://ddragon.leagueoflegends.com/cdn/7.14.1/img/spell/VelkozR.png"], "plat": {"MIDDLE": {"skill_order": ["w", "q", "e", "w", "w", "r", "w", "w", "q", "q", "r", "q", "q", "e", "e", "r", "e", "e"], "stats": {"Win Rate": "52.92%", "Pick Rate": "2.48%", "Ban Rate": "0.06%", "Gold Earned": "11913", "Kills": "7.04", "Deaths": "5.54", "Assists": "7.86", "Damage Dealt": "25175.80", "Damage Taken": "16241.60", "Minions Killed": "172"}, "build": [{"src": "https://ddragon.leagueoflegends.com/cdn/7.14.1/img/item/3165.png", "id": "3165"}, {"src": "https://ddragon.leagueoflegends.com/cdn/7.14.1/img/item/3020.png", "id": "3020"}, {"src": "https://ddragon.leagueoflegends.com/cdn/7.14.1/img/item/3285.png", "id": "3285"}, {"src": "https://ddragon.leagueoflegends.com/cdn/7.14.1/img/item/3151.png", "id": "3151"}, {"src": "https://ddragon.leagueoflegends.com/cdn/7.14.1/img/item/3135.png", "id": "3135"}, {"src": "https://ddragon.leagueoflegends.com/cdn/7.14.1/img/item/3116.png", "id": "3116"}], "counters": {"weak": [{"name": "Brand", "win_rate": "45.10%", "img": "https://ddragon.leagueoflegends.com/cdn/7.19.1/img/champion/Brand.png"}, {"name": "Aurelion Sol", "win_rate": "45.98%", "img": "https://ddragon.leagueoflegends.com/cdn/7.19.1/img/champion/AurelionSol.png"}, {"name": "Ahri", "win_rate": "47.19%", "img": "https://ddragon.leagueoflegends.com/cdn/7.19.1/img/champion/Ahri.png"}, {"name": "Diana", "win_rate": "47.44%", "img": "https://ddragon.leagueoflegends.com/cdn/7.19.1/img/champion/Diana.png"}, {"name": "Ziggs", "win_rate": "47.49%", "img": "https://ddragon.leagueoflegends.com/cdn/7.19.1/img/champion/Ziggs.png"}], "strong": [{"name": "Morgana", "win_rate": "63.11%", "img": "https://ddragon.leagueoflegends.com/cdn/7.19.1/img/champion/Morgana.png"}, {"name": "Akali", "win_rate": "62.86%", "img": "https://ddragon.leagueoflegends.com/cdn/7.19.1/img/champion/Akali.png"}, {"name": "Jayce", "win_rate": "62.75%", "img": "https://ddragon.leagueoflegends.com/cdn/7.19.1/img/champion/Jayce.png"}, {"name": "Galio", "win_rate": "61.24%", "img": "https://ddragon.leagueoflegends.com/cdn/7.19.1/img/champion/Galio.png"}, {"name": "Azir", "win_rate": "60.80%", "img": "https://ddragon.leagueoflegends.com/cdn/7.19.1/img/champion/Azir.png"}]}}, "SUPPORT": {"skill_order": ["q", "w", "q", "e", "q", "r", "q", "w", "q", "w", "r", "w", "w", "e", "e", "r", "e", "e"], "stats": {"Win Rate": "48.76%", "Pick Rate": "0.90%", "Ban Rate": "0.06%", "Gold Earned": "10798", "Kills": "4.72", "Deaths": "6.36", "Assists": "10.25", "Damage Dealt": "21557.40", "Damage Taken": "15657.70", "Minions Killed": "45"}, "build": [{"src": "https://ddragon.leagueoflegends.com/cdn/7.14.1/img/item/2301.png", "id": "2301"}, {"src": "https://ddragon.leagueoflegends.com/cdn/7.14.1/img/item/3020.png", "id": "3020"}, {"src": "https://ddragon.leagueoflegends.com/cdn/7.14.1/img/item/3151.png", "id": "3151"}, {"src": "https://ddragon.leagueoflegends.com/cdn/7.14.1/img/item/3116.png", "id": "3116"}, {"src": "https://ddragon.leagueoflegends.com/cdn/7.14.1/img/item/3135.png", "id": "3135"}, {"src": "https://ddragon.leagueoflegends.com/cdn/7.14.1/img/item/3285.png", "id": "3285"}], "counters": {"weak": [{"name": "Sona", "win_rate": "37.45%", "img": "https://ddragon.leagueoflegends.com/cdn/7.19.1/img/champion/Sona.png"}, {"name": "Soraka", "win_rate": "42.89%", "img": "https://ddragon.leagueoflegends.com/cdn/7.19.1/img/champion/Soraka.png"}, {"name": "Janna", "win_rate": "44.51%", "img": "https://ddragon.leagueoflegends.com/cdn/7.19.1/img/champion/Janna.png"}, {"name": "Karma", "win_rate": "44.62%", "img": "https://ddragon.leagueoflegends.com/cdn/7.19.1/img/champion/Karma.png"}, {"name": "Nami", "win_rate": "45.08%", "img": "https://ddragon.leagueoflegends.com/cdn/7.19.1/img/champion/Nami.png"}], "strong": [{"name": "Zyra", "win_rate": "54.64%", "img": "https://ddragon.leagueoflegends.com/cdn/7.19.1/img/champion/Zyra.png"}, {"name": "Thresh", "win_rate": "53.73%", "img": "https://ddragon.leagueoflegends.com/cdn/7.19.1/img/champion/Thresh.png"}, {"name": "Braum", "win_rate": "53.53%", "img": "https://ddragon.leagueoflegends.com/cdn/7.19.1/img/champion/Braum.png"}, {"name": "Rakan", "win_rate": "52.38%", "img": "https://ddragon.leagueoflegends.com/cdn/7.19.1/img/champion/Rakan.png"}, {"name": "Alistar", "win_rate": "51.76%", "img": "https://ddragon.leagueoflegends.com/cdn/7.19.1/img/champion/Alistar.png"}]}}}, "gold": {"MIDDLE": {"skill_order": ["q", "w", "e", "w", "q", "r", "q", "e", "q", "e", "r", "e", "e", "w", "w", "r", "w", "q"], "stats": {"Win Rate": "53.44%", "Pick Rate": "2.39%", "Ban Rate": "0.08%", "Gold Earned": "11994", "Kills": "7.34", "Deaths": "5.88", "Assists": "8.08", "Damage Dealt": "25531.30", "Damage Taken": "16562.80", "Minions Killed": "166"}, "build": [{"src": "https://ddragon.leagueoflegends.com/cdn/7.14.1/img/item/3165.png", "id": "3165"}, {"src": "https://ddragon.leagueoflegends.com/cdn/7.14.1/img/item/3020.png", "id": "3020"}, {"src": "https://ddragon.leagueoflegends.com/cdn/7.14.1/img/item/3285.png", "id": "3285"}, {"src": "https://ddragon.leagueoflegends.com/cdn/7.14.1/img/item/3151.png", "id": "3151"}, {"src": "https://ddragon.leagueoflegends.com/cdn/7.14.1/img/item/3135.png", "id": "3135"}, {"src": "https://ddragon.leagueoflegends.com/cdn/7.14.1/img/item/3089.png", "id": "3089"}], "counters": {"weak": [{"name": "Karthus", "win_rate": "39.24%", "img": "https://ddragon.leagueoflegends.com/cdn/7.19.1/img/champion/Karthus.png"}, {"name": "Fizz", "win_rate": "44.23%", "img": "https://ddragon.leagueoflegends.com/cdn/7.19.1/img/champion/Fizz.png"}, {"name": "Xerath", "win_rate": "46.67%", "img": "https://ddragon.leagueoflegends.com/cdn/7.19.1/img/champion/Xerath.png"}, {"name": "Malzahar", "win_rate": "47.21%", "img": "https://ddragon.leagueoflegends.com/cdn/7.19.1/img/champion/Malzahar.png"}, {"name": "Morgana", "win_rate": "48.57%", "img": "https://ddragon.leagueoflegends.com/cdn/7.19.1/img/champion/Morgana.png"}], "strong": [{"name": "Cassiopeia", "win_rate": "64.50%", "img": "https://ddragon.leagueoflegends.com/cdn/7.19.1/img/champion/Cassiopeia.png"}, {"name": "Azir", "win_rate": "63.01%", "img": "https://ddragon.leagueoflegends.com/cdn/7.19.1/img/champion/Azir.png"}, {"name": "Lucian", "win_rate": "60.40%", "img": "https://ddragon.leagueoflegends.com/cdn/7.19.1/img/champion/Lucian.png"}, {"name": "Lissandra", "win_rate": "59.76%", "img": "https://ddragon.leagueoflegends.com/cdn/7.19.1/img/champion/Lissandra.png"}, {"name": "Corki", "win_rate": "59.04%", "img": "https://ddragon.leagueoflegends.com/cdn/7.19.1/img/champion/Corki.png"}]}}, "SUPPORT": {"skill_order": ["q", "w", "e", "q", "q", "r", "q", "w", "q", "w", "r", "w", "w", "e", "e", "r", "e", "e"], "stats": {"Win Rate": "50.64%", "Pick Rate": "0.96%", "Ban Rate": "0.08%", "Gold Earned": "11022", "Kills": "4.92", "Deaths": "6.47", "Assists": "10.47", "Damage Dealt": "21872.70", "Damage Taken": "15840.40", "Minions Killed": "48"}, "build": [{"src": "https://ddragon.leagueoflegends.com/cdn/7.14.1/img/item/3092.png", "id": "3092"}, {"src": "https://ddragon.leagueoflegends.com/cdn/7.14.1/img/item/3020.png", "id": "3020"}, {"src": "https://ddragon.leagueoflegends.com/cdn/7.14.1/img/item/3151.png", "id": "3151"}, {"src": "https://ddragon.leagueoflegends.com/cdn/7.14.1/img/item/3116.png", "id": "3116"}, {"src": "https://ddragon.leagueoflegends.com/cdn/7.14.1/img/item/2045.png", "id": "2045"}, {"src": "https://ddragon.leagueoflegends.com/cdn/7.14.1/img/item/3157.png", "id": "3157"}], "counters": {"weak": [{"name": "Sona", "win_rate": "41.73%", "img": "https://ddragon.leagueoflegends.com/cdn/7.19.1/img/champion/Sona.png"}, {"name": "Brand", "win_rate": "42.37%", "img": "https://ddragon.leagueoflegends.com/cdn/7.19.1/img/champion/Brand.png"}, {"name": "Soraka", "win_rate": "43.61%", "img": "https://ddragon.leagueoflegends.com/cdn/7.19.1/img/champion/Soraka.png"}, {"name": "Zyra", "win_rate": "45.90%", "img": "https://ddragon.leagueoflegends.com/cdn/7.19.1/img/champion/Zyra.png"}, {"name": "Leona", "win_rate": "46.01%", "img": "https://ddragon.leagueoflegends.com/cdn/7.19.1/img/champion/Leona.png"}], "strong": [{"name": "Morgana", "win_rate": "61.45%", "img": "https://ddragon.leagueoflegends.com/cdn/7.19.1/img/champion/Morgana.png"}, {"name": "Braum", "win_rate": "58.33%", "img": "https://ddragon.leagueoflegends.com/cdn/7.19.1/img/champion/Braum.png"}, {"name": "Bard", "win_rate": "55.30%", "img": "https://ddragon.leagueoflegends.com/cdn/7.19.1/img/champion/Bard.png"}, {"name": "Rakan", "win_rate": "54.93%", "img": "https://ddragon.leagueoflegends.com/cdn/7.19.1/img/champion/Rakan.png"}, {"name": "Lux", "win_rate": "53.54%", "img": "https://ddragon.leagueoflegends.com/cdn/7.19.1/img/champion/Lux.png"}]}}}, "silver": {"MIDDLE": {"skill_order": ["w", "q", "e", "q", "q", "r", "q", "e", "e", "q", "r", "w", "w", "e", "e", "r", "w", "w"], "stats": {"Win Rate": "53.14%", "Pick Rate": "2.25%", "Ban Rate": "0.09%", "Gold Earned": "11979", "Kills": "7.59", "Deaths": "6.08", "Assists": "8.16", "Damage Dealt": "25772.00", "Damage Taken": "16790.40", "Minions Killed": "159"}, "build": [{"src": "https://ddragon.leagueoflegends.com/cdn/7.14.1/img/item/3165.png", "id": "3165"}, {"src": "https://ddragon.leagueoflegends.com/cdn/7.14.1/img/item/3158.png", "id": "3158"}, {"src": "https://ddragon.leagueoflegends.com/cdn/7.14.1/img/item/3285.png", "id": "3285"}, {"src": "https://ddragon.leagueoflegends.com/cdn/7.14.1/img/item/3116.png", "id": "3116"}, {"src": "https://ddragon.leagueoflegends.com/cdn/7.14.1/img/item/3089.png", "id": "3089"}, {"src": "https://ddragon.leagueoflegends.com/cdn/7.14.1/img/item/3157.png", "id": "3157"}], "counters": {"weak": [{"name": "Malzahar", "win_rate": "44.02%", "img": "https://ddragon.leagueoflegends.com/cdn/7.19.1/img/champion/Malzahar.png"}, {"name": "Ziggs", "win_rate": "45.05%", "img": "https://ddragon.leagueoflegends.com/cdn/7.19.1/img/champion/Ziggs.png"}, {"name": "Ahri", "win_rate": "45.34%", "img": "https://ddragon.leagueoflegends.com/cdn/7.19.1/img/champion/Ahri.png"}, {"name": "Akali", "win_rate": "47.55%", "img": "https://ddragon.leagueoflegends.com/cdn/7.19.1/img/champion/Akali.png"}, {"name": "Corki", "win_rate": "47.57%", "img": "https://ddragon.leagueoflegends.com/cdn/7.19.1/img/champion/Corki.png"}], "strong": [{"name": "Talon", "win_rate": "64.55%", "img": "https://ddragon.leagueoflegends.com/cdn/7.19.1/img/champion/Talon.png"}, {"name": "Ryze", "win_rate": "63.87%", "img": "https://ddragon.leagueoflegends.com/cdn/7.19.1/img/champion/Ryze.png"}, {"name": "Cassiopeia", "win_rate": "60.56%", "img": "https://ddragon.leagueoflegends.com/cdn/7.19.1/img/champion/Cassiopeia.png"}, {"name": "Azir", "win_rate": "60.00%", "img": "https://ddragon.leagueoflegends.com/cdn/7.19.1/img/champion/Azir.png"}, {"name": "Taliyah", "win_rate": "58.97%", "img": "https://ddragon.leagueoflegends.com/cdn/7.19.1/img/champion/Taliyah.png"}]}}, "SUPPORT": {"skill_order": ["w", "q", "e", "w", "w", "r", "w", "q", "w", "q", "r", "q", "q", "e", "e", "r", "e", "e"], "stats": {"Win Rate": "50.00%", "Pick Rate": "0.87%", "Ban Rate": "0.09%", "Gold Earned": "11001", "Kills": "4.97", "Deaths": "6.51", "Assists": "10.32", "Damage Dealt": "21462.10", "Damage Taken": "15864.80", "Minions Killed": "49"}, "build": [{"src": "https://ddragon.leagueoflegends.com/cdn/7.14.1/img/item/3092.png", "id": "3092"}, {"src": "https://ddragon.leagueoflegends.com/cdn/7.14.1/img/item/3020.png", "id": "3020"}, {"src": "https://ddragon.leagueoflegends.com/cdn/7.14.1/img/item/3165.png", "id": "3165"}, {"src": "https://ddragon.leagueoflegends.com/cdn/7.14.1/img/item/3285.png", "id": "3285"}, {"src": "https://ddragon.leagueoflegends.com/cdn/7.14.1/img/item/3116.png", "id": "3116"}, {"src": "https://ddragon.leagueoflegends.com/cdn/7.14.1/img/item/3151.png", "id": "3151"}], "counters": {"weak": [{"name": "Taric", "win_rate": "41.56%", "img": "https://ddragon.leagueoflegends.com/cdn/7.19.1/img/champion/Taric.png"}, {"name": "Zyra", "win_rate": "44.30%", "img": "https://ddragon.leagueoflegends.com/cdn/7.19.1/img/champion/Zyra.png"}, {"name": "Leona", "win_rate": "44.95%", "img": "https://ddragon.leagueoflegends.com/cdn/7.19.1/img/champion/Leona.png"}, {"name": "Soraka", "win_rate": "46.95%", "img": "https://ddragon.leagueoflegends.com/cdn/7.19.1/img/champion/Soraka.png"}, {"name": "Nami", "win_rate": "47.10%", "img": "https://ddragon.leagueoflegends.com/cdn/7.19.1/img/champion/Nami.png"}], "strong": [{"name": "Morgana", "win_rate": "57.87%", "img": "https://ddragon.leagueoflegends.com/cdn/7.19.1/img/champion/Morgana.png"}, {"name": "Braum", "win_rate": "55.34%", "img": "https://ddragon.leagueoflegends.com/cdn/7.19.1/img/champion/Braum.png"}, {"name": "Bard", "win_rate": "54.64%", "img": "https://ddragon.leagueoflegends.com/cdn/7.19.1/img/champion/Bard.png"}, {"name": "Alistar", "win_rate": "52.94%", "img": "https://ddragon.leagueoflegends.com/cdn/7.19.1/img/champion/Alistar.png"}, {"name": "Lulu", "win_rate": "51.50%", "img": "https://ddragon.leagueoflegends.com/cdn/7.19.1/img/champion/Lulu.png"}]}}}, "bronze": {"MIDDLE": {"skill_order": ["w", "q", "e", "w", "q", "r", "w", "q", "w", "q", "r", "w", "e", "q", "e", "r", "e", "e"], "stats": {"Win Rate": "52.52%", "Pick Rate": "2.00%", "Ban Rate": "0.12%", "Gold Earned": "11918", "Kills": "7.92", "Deaths": "6.45", "Assists": "8.42", "Damage Dealt": "25936.40", "Damage Taken": "17188.30", "Minions Killed": "147"}, "build": [{"src": "https://ddragon.leagueoflegends.com/cdn/7.14.1/img/item/3165.png", "id": "3165"}, {"src": "https://ddragon.leagueoflegends.com/cdn/7.14.1/img/item/3158.png", "id": "3158"}, {"src": "https://ddragon.leagueoflegends.com/cdn/7.14.1/img/item/3285.png", "id": "3285"}, {"src": "https://ddragon.leagueoflegends.com/cdn/7.14.1/img/item/3116.png", "id": "3116"}, {"src": "https://ddragon.leagueoflegends.com/cdn/7.14.1/img/item/3089.png", "id": "3089"}, {"src": "https://ddragon.leagueoflegends.com/cdn/7.14.1/img/item/3157.png", "id": "3157"}], "counters": {"weak": [{"name": "Anivia", "win_rate": "43.59%", "img": "https://ddragon.leagueoflegends.com/cdn/7.19.1/img/champion/Anivia.png"}, {"name": "Katarina", "win_rate": "44.94%", "img": "https://ddragon.leagueoflegends.com/cdn/7.19.1/img/champion/Katarina.png"}, {"name": "Ekko", "win_rate": "46.39%", "img": "https://ddragon.leagueoflegends.com/cdn/7.19.1/img/champion/Ekko.png"}, {"name": "Brand", "win_rate": "46.67%", "img": "https://ddragon.leagueoflegends.com/cdn/7.19.1/img/champion/Brand.png"}, {"name": "Malzahar", "win_rate": "47.03%", "img": "https://ddragon.leagueoflegends.com/cdn/7.19.1/img/champion/Malzahar.png"}], "strong": [{"name": "Cassiopeia", "win_rate": "72.50%", "img": "https://ddragon.leagueoflegends.com/cdn/7.19.1/img/champion/Cassiopeia.png"}, {"name": "Ryze", "win_rate": "62.50%", "img": "https://ddragon.leagueoflegends.com/cdn/7.19.1/img/champion/Ryze.png"}, {"name": "Heimerdinger", "win_rate": "62.00%", "img": "https://ddragon.leagueoflegends.com/cdn/7.19.1/img/champion/Heimerdinger.png"}, {"name": "Leblanc", "win_rate": "60.16%", "img": "https://ddragon.leagueoflegends.com/cdn/7.19.1/img/champion/Leblanc.png"}, {"name": "Annie", "win_rate": "58.60%", "img": "https://ddragon.leagueoflegends.com/cdn/7.19.1/img/champion/Annie.png"}]}}, "SUPPORT": {"skill_order": ["q", "e", "w", "w", "w", "r", "w", "q", "w", "q", "r", "q", "q", "e", "e", "e", "r", "e"], "stats": {"Win Rate": "52.87%", "Pick Rate": "0.72%", "Ban Rate": "0.12%", "Gold Earned": "11139", "Kills": "5.16", "Deaths": "6.62", "Assists": "10.49", "Damage Dealt": "21625.40", "Damage Taken": "16031.90", "Minions Killed": "52"}, "build": [{"src": "https://ddragon.leagueoflegends.com/cdn/7.14.1/img/item/3092.png", "id": "3092"}, {"src": "https://ddragon.leagueoflegends.com/cdn/7.14.1/img/item/3158.png", "id": "3158"}, {"src": "https://ddragon.leagueoflegends.com/cdn/7.14.1/img/item/3165.png", "id": "3165"}, {"src": "https://ddragon.leagueoflegends.com/cdn/7.14.1/img/item/3285.png", "id": "3285"}, {"src": "https://ddragon.leagueoflegends.com/cdn/7.14.1/img/item/3116.png", "id": "3116"}, {"src": "https://ddragon.leagueoflegends.com/cdn/7.14.1/img/item/3089.png", "id": "3089"}], "counters": {"weak": [{"name": "Janna", "win_rate": "41.67%", "img": "https://ddragon.leagueoflegends.com/cdn/7.19.1/img/champion/Janna.png"}, {"name": "Sona", "win_rate": "48.23%", "img": "https://ddragon.leagueoflegends.com/cdn/7.19.1/img/champion/Sona.png"}, {"name": "Soraka", "win_rate": "50.82%", "img": "https://ddragon.leagueoflegends.com/cdn/7.19.1/img/champion/Soraka.png"}, {"name": "Blitzcrank", "win_rate": "51.20%", "img": "https://ddragon.leagueoflegends.com/cdn/7.19.1/img/champion/Blitzcrank.png"}, {"name": "Thresh", "win_rate": "52.45%", "img": "https://ddragon.leagueoflegends.com/cdn/7.19.1/img/champion/Thresh.png"}], "strong": [{"name": "Morgana", "win_rate": "56.00%", "img": "https://ddragon.leagueoflegends.com/cdn/7.19.1/img/champion/Morgana.png"}, {"name": "Leona", "win_rate": "55.63%", "img": "https://ddragon.leagueoflegends.com/cdn/7.19.1/img/champion/Leona.png"}, {"name": "Lulu", "win_rate": "55.26%", "img": "https://ddragon.leagueoflegends.com/cdn/7.19.1/img/champion/Lulu.png"}, {"name": "Rakan", "win_rate": "54.95%", "img": "https://ddragon.leagueoflegends.com/cdn/7.19.1/img/champion/Rakan.png"}, {"name": "Lux", "win_rate": "53.41%", "img": "https://ddragon.leagueoflegends.com/cdn/7.19.1/img/champion/Lux.png"}]}}}}