{"platplus": {"MIDDLE": {"skill_order": ["q", "w", "e", "e", "q", "r", "q", "q", "e", "e", "r", "q", "e", "w", "w", "r", "w", "w"], "stats": {"Win Rate": "49.95%", "Pick Rate": "7.83%", "Ban Rate": "4.56%", "Gold Earned": "11999", "Kills": "8.62", "Deaths": "6.06", "Assists": "5.29", "Damage Dealt": "21337.40", "Damage Taken": "19667.20", "Minions Killed": "172"}}}, "skillImages": ["https://ddragon.leagueoflegends.com/cdn/7.14.1/img/spell/ZedQ.png", "https://ddragon.leagueoflegends.com/cdn/7.14.1/img/spell/ZedW.png", "https://ddragon.leagueoflegends.com/cdn/7.14.1/img/spell/ZedE.png", "https://ddragon.leagueoflegends.com/cdn/7.14.1/img/spell/ZedR.png"], "plat": {"MIDDLE": {"skill_order": ["q", "w", "e", "e", "q", "r", "q", "q", "e", "e", "r", "q", "e", "w", "w", "r", "w", "w"], "stats": {"Win Rate": "49.93%", "Pick Rate": "8.12%", "Ban Rate": "5.23%", "Gold Earned": "12142", "Kills": "8.85", "Deaths": "6.22", "Assists": "5.44", "Damage Dealt": "21750.80", "Damage Taken": "20100.50", "Minions Killed": "171"}}}, "gold": {"MIDDLE": {"skill_order": ["q", "e", "w", "w", "q", "r", "e", "q", "e", "w", "r", "e", "q", "e", "w", "r", "q", "w"], "stats": {"Win Rate": "49.47%", "Pick Rate": "8.01%", "Ban Rate": "5.75%", "Gold Earned": "12267", "Kills": "9.13", "Deaths": "6.50", "Assists": "5.66", "Damage Dealt": "22179.60", "Damage Taken": "20720.40", "Minions Killed": "167"}}}, "silver": {"MIDDLE": {"skill_order": ["q", "e", "w", "q", "e", "r", "w", "q", "e", "w", "r", "q", "e", "w", "q", "r", "e", "w"], "stats": {"Win Rate": "49.46%", "Pick Rate": "8.26%", "Ban Rate": "5.78%", "Gold Earned": "12288", "Kills": "9.43", "Deaths": "6.79", "Assists": "5.87", "Damage Dealt": "22496.20", "Damage Taken": "21157.40", "Minions Killed": "160"}}}, "bronze": {"MIDDLE": {"skill_order": ["q", "w", "e", "w", "w", "r", "q", "e", "w", "q", "r", "e", "w", "q", "q", "r", "e", "e"], "stats": {"Win Rate": "49.43%", "Pick Rate": "8.61%", "Ban Rate": "5.41%", "Gold Earned": "12205", "Kills": "9.68", "Deaths": "7.21", "Assists": "6.10", "Damage Dealt": "22707.70", "Damage Taken": "21657.10", "Minions Killed": "149"}}}}